<?xml version="1.0" encoding="utf-8" ?>
<SourceTabSettings>
  <!--<Controls foldername ="Rotator">	
		<Samples name ="APIs" >
		     //sample name which was same as in samplelist.js file 
			<dependantfiles displayname ="Properties.Js" url="~\Rotator\Scripts\Properties.js"/>
			//displayname = Title of the tab
			// url = page to load on that tab content
		</Samples>
	</Controls>-->
  <Controls foldername ="ComboBox">
    <Samples name ="Api" >
      <dependantfiles displayname ="flowers.cs" url="~\App_Data\Flowers.cs"/>
    </Samples>
    <Samples name ="ClientSideEvents" >
      <dependantfiles displayname ="colors.cs" url="~\App_Data\Colors.cs"/>
    </Samples>
    <Samples name ="Databinding-Local" >
      <dependantfiles displayname ="states.cs" url="~\App_Data\States.cs"/>
    </Samples>
    <Samples name ="DataBinding-ObjectData" >
      <dependantfiles displayname ="tabdata.cs" url="~\App_Data\TabData.cs"/>
    </Samples>
    <Samples name ="DataBinding-XMLData" >
      <dependantfiles displayname ="xmldata.xml" url="~\App_Data/XMLData.xml"/>
    </Samples>
   <Samples name ="DefaultFunctionalities" >
      <dependantfiles displayname ="carslist.cs" url="~\App_Data/CarsList.cs"/>
    </Samples>
   <Samples name ="Events" >
      <dependantfiles displayname ="colors.cs" url="~\App_Data/Colors.cs"/>
    </Samples>
  <Samples name ="Filtering" >
      <dependantfiles displayname ="countries.cs" url="~\App_Data/Countries.cs"/>
    </Samples>
  <Samples name ="Grouping" >
      <dependantfiles displayname ="countries.cs" url="~\App_Data/Countries.cs"/>
    </Samples>
  <Samples name ="RTL" >
      <dependantfiles displayname ="carslist.cs" url="~\App_Data/CarsList.cs"/>
    </Samples>
  </Controls>
  <Controls foldername ="DropDownList">
    <Samples name ="DataBinding-Locatdata" >
      <dependantfiles displayname ="tabdata.cs" url="~\App_Data\TabData.cs"/>
    </Samples>
     <Samples name ="DataBinding-ObjectData" >
      <dependantfiles displayname ="tabdata.cs" url="~\App_Data\TabData.cs"/>
    </Samples>
    <Samples name ="DataBinding-XMLData" >
      <dependantfiles displayname ="xmldata.xml" url="~\App_Data/XMLData.xml"/>
    </Samples>
    <Samples name ="MultiSelect" >
      <dependantfiles displayname ="lanuages.cs" url="~\App_Data\Lanuages.cs"/>
    </Samples>
    <Samples name ="RTL" >
      <dependantfiles displayname ="lanuages.cs" url="~\App_Data\Lanuages.cs"/>
    </Samples>
  </Controls>
  <Controls foldername ="Menu">
    <Samples name ="DataBinding-Object" >
      <dependantfiles displayname ="menusource.cs" url="~\App_Data\MenuSource.cs"/>
    </Samples>
    <Samples name ="DataBinding-XML" >
      <dependantfiles displayname ="xmldata.xml" url="~\App_Data/XMLData.xml"/>
    </Samples>

  </Controls>
  <Controls foldername ="TagCloud">
    <Samples name ="ClientSideEvents" >
      <dependantfiles displayname ="tagclouddata.cs" url="~\App_Data\MenuSource.cs"/>
    </Samples>
    <Samples name ="DefaultFunctionalities" >
      <dependantfiles displayname ="tagclouddata.cs" url="~\App_Data/TagCloudData.cs"/>
    </Samples>
  <Samples name ="Events" >
    <dependantfiles displayname ="tagclouddata.cs" url="~\App_Data/TagCloudData.cs"/>
    </Samples>
  <Samples name ="RTL" >
    <dependantfiles displayname ="tagclouddata.cs" url="~\App_Data/TagCloudData.cs"/>
    </Samples>
  </Controls>  
  <Controls foldername ="RangeNavigator">
    <Samples name ="RangeRTL" >
      <dependantfiles displayname ="datapoints.cs" url="~\App_Data\DataPoints.cs"/>
    </Samples>    
  </Controls>   
  <Controls foldername ="Sparkline">
    <Samples name ="Sparklinegrid" >
      <dependantfiles displayname ="orders.cs" url="~\App_Data\Orders.cs"/>
    </Samples>    
  </Controls>
  <Controls foldername ="TreeMap">
    <Samples name ="Customization">
      <dependantfiles displayname ="medaldata.cs" url="~\App_Data\TreeMap\MedalData.cs"/> 
    </Samples>	  
    <Samples name ="FlatCollection">
      <dependantfiles displayname ="treemappopulationdata.cs" url="~\App_Data\TreeMap\TreeMapPopulationData.cs"/>
    </Samples>  		         
    <Samples name ="DrillDown">
      <dependantfiles displayname ="populationdata.cs" url="~\App_Data\TreeMap\PopulationData.cs"/>
    </Samples> 	
  </Controls>
  <Controls foldername ="SunburstChart">
    <Samples name ="Animation" >
      <dependantfiles displayname ="animationdata.cs" url="~\App_Data\Sunburst\AnimationData.cs"/>
    </Samples>    
	<Samples name ="Default" >
      <dependantfiles displayname ="defaultdata.cs" url="~\App_Data\Sunburst\DefaultData.cs"/>
    </Samples> 
	<Samples name ="Selection" >
      <dependantfiles displayname ="selectiondata.cs" url="~\App_Data\Sunburst\SelectionData.cs"/>
    </Samples> 
	<Samples name ="Zooming" >
      <dependantfiles displayname ="zoomingdata.cs" url="~\App_Data\Sunburst\ZoomingData.cs"/>
    </Samples> 
  </Controls>
  

  <Controls foldername ="Rotator">
    <Samples name ="APIs" >
      <dependantfiles displayname ="Js" url="~\Scripts\Rotator\Properties.js"/>
      <dependantfiles displayname ="Css" url="~\Content\Rotator\API.css"/>
    </Samples>
    <Samples name ="ImagewithContent" >
      <dependantfiles displayname ="Css" url="~\Content\Rotator\ImagewithContent.css"/>
    </Samples>
    <Samples name ="Keyboard-Interaction" >
      <dependantfiles displayname ="Js" url="~\Scripts\Rotator\KeyboardInteraction.js"/>
    </Samples>
    <Samples name ="KnockoutSupport" >
      <dependantfiles displayname ="Js" url="~\Scripts\Rotator\KnockoutSupport.js"/>
    </Samples>
    <Samples name ="Thumbnail" >
      <dependantfiles displayname ="Css" url="~\Content\Rotator\Thumbnail.css"/>
    </Samples>
  </Controls>

  <Controls foldername ="ProgressBar">
    <Samples name ="APIs" >
      <dependantfiles displayname ="Js" url="~\Scripts\ProgressBar\events.js"/>
    </Samples>
  </Controls>
  <Controls foldername ="TreeView">
    <Samples name ="Icons">
      <dependantfiles displayname ="CSS" url="~\Content\TreeView\Icons.css"/>
    </Samples>
    <Samples name ="Template" >
      <dependantfiles displayname ="CSS" url="~\Content\TreeView\Template.css"/>
    </Samples>
    <Samples name ="Events" >
      <dependantfiles displayname ="Js" url="~\Scripts\TreeView\Events.js"/>
    </Samples>
    <Samples name ="APIs" >
      <dependantfiles displayname ="Js" url="~\Scripts\TreeView\APIs.js"/>
    </Samples>
  </Controls>
  <Controls foldername ="AutoComplete">
    <Samples name ="Template">
      <dependantfiles displayname ="CSS" url="~\Content\AutoComplete\Template.css"/>
    </Samples>
    <Samples name ="KnockoutSupport" >
      <dependantfiles displayname ="Js" url="~\Scripts\AutoComplete\KnockoutSupport.js"/>
    </Samples>    
  </Controls>
  <Controls foldername ="Textboxes">
    <Samples name ="KnockoutSupport">
      <dependantfiles displayname ="Js" url="~\Scripts\TextBox\KnockoutSupport.js"/>
    </Samples>
    <Samples name ="APIs" >
      <dependantfiles displayname ="Js" url="~\Scripts\TextBox\APIs.js"/>
    </Samples>
    <Samples name ="ClientSideEvents" >
      <dependantfiles displayname ="Events.js" url="~\Scripts\TextBox\Events.js"/>
    </Samples>
  </Controls>
  <Controls foldername ="TagCloud">
    <Samples name ="Events">
      <dependantfiles displayname ="Js" url="~\Scripts\TagCloud\Events.js"/>
    </Samples>
  </Controls>
  <Controls foldername="RichTextEditor" >
    <Samples name ="API" >
      <dependantfiles displayname ="API.js" url="~\Scripts\RichTextEditor\APIJs.js"/>
    </Samples>
    <Samples name ="Events" >
      <dependantfiles displayname ="Events.js" url="~\Scripts\RichTextEditor\Events.js"/>
    </Samples>
    <Samples name ="Localization" >
      <dependantfiles displayname ="Localization.js" url="~\Scripts\RichTextEditor\localizationScripts.js"/>
    </Samples>
  </Controls>
  <Controls foldername="Splitter" >
    <Samples name ="DefaultFunctionalities" >
      <dependantfiles displayname ="Js" url="~\Scripts\Splitter\API.js"/>
    </Samples>
    <Samples name ="Orientation" >
      <dependantfiles displayname ="js" url="~\Scripts\Splitter\Orientation.js"/>
    </Samples>
    <Samples name ="APIs" >
      <dependantfiles displayname ="js" url="~\Scripts\Splitter\API.js"/>
    </Samples>
    <Samples name ="Events" >
      <dependantfiles displayname ="js" url="~\Scripts\Splitter\Events.js"/>
    </Samples>
    <Samples name ="Keyboard-Interaction" >
      <dependantfiles displayname ="js" url="~\Scripts\Splitter\Keyboardinteraction.js"/>
    </Samples>
  </Controls>
  <Controls foldername ="Accordion">
    <Samples name ="API" >
      <dependantfiles displayname ="Script" url="~\Scripts\Accordion\AccordionAPI.js"/>
    </Samples>
    <Samples name ="DefaultFunctionalities" >
      <dependantfiles displayname ="Css" url="~\Content\Accordion\defaultfunctionalities.css"/>
    </Samples>
    <Samples name ="Icons" >
      <dependantfiles displayname ="Css" url="~\Content\Accordion\icons.css"/>
    </Samples>
    <Samples name ="Events" >
      <dependantfiles displayname ="Js" url="~\Scripts\Accordion\events.js"/>
    </Samples>
  </Controls>
  <Controls foldername ="Toolbar">
    <Samples name ="AngularSupport" >
      <dependantfiles displayname ="CSS" url="~\Content\Toolbar\angularsupport.css"/>
    </Samples>
    <Samples name ="DataBinding-LocalData" >
      <dependantfiles displayname ="CSS" url="~\Content\Toolbar\databinding-localdata.css"/>
    </Samples>
    <Samples name ="DataBinding-ObjectData" >
      <dependantfiles displayname ="CSS" url="~\Content\Content\Toolbar\ObjectTool.css"/>
    </Samples>
    <Samples name ="DataBinding-RemoteData" >
      <dependantfiles displayname ="CSS" url="~\Content\Toolbar\databinding-remotedata.css"/>
    </Samples>
    <Samples name ="DataBinding-XML" >
      <dependantfiles displayname ="CSS" url="~\Content\Toolbar\BasicTool.css"/>
    </Samples>
    <Samples name ="DataBinding-SqlData" >
      <dependantfiles displayname ="CSS" url="~\Content\Toolbar\rtl.css"/>
    </Samples>
    <Samples name ="DefaultFunctionalities" >
      <dependantfiles displayname ="CSS" url="~\Content\Toolbar\defaultfunctionalites.css"/>
    </Samples>
    <Samples name ="Events" >
      <dependantfiles displayname ="CSS" url="~\Content\Toolbar\events.css"/>
      <dependantfiles displayname ="JS" url="~\Scripts\Toolbar\toolbarevent.js"/>
    </Samples>
    <Samples name ="API">
      <dependantfiles displayname ="CSS" url="~\Content\Toolbar\API.css"/>
      <dependantfiles displayname ="JS" url="~\Scripts\Toolbar\toolbarapi.js"/>
    </Samples>
    <Samples name ="KeyboardInteraction" >
      <dependantfiles displayname ="CSS" url="~\Content\Toolbar\keyboardinteraction.css"/>
    </Samples>
    <Samples name ="KnockoutSupport" >
      <dependantfiles displayname ="CSS" url="~\Content\Toolbar\knockoutsupport.css"/>
    </Samples>
    <Samples name ="Orientation" >
      <dependantfiles displayname ="CSS" url="~\Content\Toolbar\orientation.css"/>
    </Samples>
    <Samples name ="RTL" >
      <dependantfiles displayname ="CSS" url="~\Content\Toolbar\rtl.css"/>
    </Samples>
    <Samples name ="Template" >
      <dependantfiles displayname ="CSS" url="~\Content\Toolbar\template.css"/>
    </Samples>
  </Controls>
  <Controls foldername ="Menu">
    <Samples name ="APIs">
      <dependantfiles displayname ="Js" url="~\Scripts\Menu\API.js"/>
    </Samples>
    <Samples name ="Templates" >
      <dependantfiles displayname ="CSS" url="~\Content\Menu\Template.css"/>
    </Samples>

  </Controls>
  <Controls foldername ="Dialog">
    <Samples name ="API">
      <dependantfiles displayname ="JS" url="~\Content\Dialog\API.js"/>
    </Samples>
    <Samples name ="AjaxContent">
      <dependantfiles displayname ="Js" url="~\Scripts\Dialog\AjaxContent.js"/>
    </Samples>
    <Samples name ="DefaultFunctionalities">
      <dependantfiles displayname ="Js" url="~\Scripts\Dialog\DefaultFunctionalities.js"/>
    </Samples>
    <Samples name ="CustomAction" >
      <dependantfiles displayname ="Js" url="~\Scripts\Dialog\CustomAction.js"/>
    </Samples>
    <Samples name ="Events">
      <dependantfiles displayname ="Js" url="~\Scripts\Dialog\Events.js"/>
    </Samples>
    <Samples name ="KeyboardIntraction" >
      <dependantfiles displayname ="Js" url="~\Scripts\Dialog\KeyboardInteraction.js"/>
    </Samples>
    <Samples name ="ModelDialog" >
      <dependantfiles displayname ="Js" url="~\Scripts\Dialog\ModalDialog.js"/>
    </Samples>
    <Samples name ="RTL" >
      <dependantfiles displayname ="Js" url="~\Scripts\Dialog\RTL.js"/>
    </Samples>
  </Controls>
  <Controls foldername ="PivotChart">
    <Samples name ="OlapWCF">
      <dependantfiles displayname ="WCF" url="~\wcf\OlapChartService.svc.cs"/>
    </Samples>
    <Samples name ="OlapWebAPI">
      <dependantfiles displayname ="WebAPI" url="~\WebAPI\OlapChartController.cs"/>
    </Samples>
    <Samples name ="RelationalWCF">
      <dependantfiles displayname ="WCF" url="~\wcf\RelationalChartService.svc.cs"/>
    </Samples>
    <Samples name ="RelationalWebAPI">
      <dependantfiles displayname ="WebAPI" url="~\WebAPI\RelationalChartController.cs"/>
    </Samples>
    <Samples name ="Events">
      <dependantfiles displayname ="WebAPI" url="~\WebAPI\OlapChartController.cs"/>
    </Samples>
  </Controls>

  <Controls foldername ="PivotGauge">
    <Samples name ="OlapWCF">
      <dependantfiles displayname ="WCF" url="~\wcf\OlapGaugeService.svc.cs"/>
    </Samples>
    <Samples name ="OlapWebAPI">
      <dependantfiles displayname ="WebAPI" url="~\WebAPI\OlapGaugeController.cs"/>
    </Samples>
    <Samples name ="RelationalWCF">
      <dependantfiles displayname ="WCF" url="~\wcf\RelationalGaugeService.svc.cs"/>
    </Samples>
    <Samples name ="RelationalWebAPI">
      <dependantfiles displayname ="WebAPI" url="~\WebAPI\RelationalGaugeController.cs"/>
    </Samples>
  </Controls>
  <Controls foldername ="PivotTreeMap">
    <Samples name ="WCF">
      <dependantfiles displayname ="WCF" url="~\wcf\OlapTreeMapService.svc.cs"/>
    </Samples>
    <Samples name ="WebAPI">
      <dependantfiles displayname ="WebAPI" url="~\WebAPI\OlapTreeMapController.cs"/>
    </Samples>
  </Controls>
  <Controls foldername ="PivotClient">
    <Samples name ="OlapWCF">
      <dependantfiles displayname ="WCF" url="~\wcf\OlapClientService.svc.cs"/>
    </Samples>
    <Samples name ="OlapWebAPI">
      <dependantfiles displayname ="WebAPI" url="~\WebAPI\OlapClientController.cs"/>
    </Samples>
    <Samples name ="RelationalWCF">
      <dependantfiles displayname ="WCF" url="~\wcf\RelationalClientService.svc.cs"/>
    </Samples>
    <Samples name ="RelationalWebAPI">
      <dependantfiles displayname ="WebAPI" url="~\WebAPI\RelationalClientController.cs"/>
    </Samples>
  </Controls>

  <Controls foldername ="PivotGrid">
    <Samples name ="OlapWCF">
      <dependantfiles displayname ="WCF" url="~\wcf\OlapGridService.svc.cs"/>
    </Samples>
    <Samples name ="OlapWebAPI">
      <dependantfiles displayname ="WebAPI" url="~\WebAPI\OlapGridController.cs"/>
    </Samples>
    <Samples name ="RelationalWCF">
      <dependantfiles displayname ="WCF" url="~\wcf\RelationalGridService.svc.cs"/>
    </Samples>
    <Samples name ="RelationalWebAPI">
      <dependantfiles displayname ="WebAPI" url="~\WebAPI\RelationalGridController.cs"/>
    </Samples>
    <Samples name ="CellEditing">
      <dependantfiles displayname ="WebAPI" url="~\WebAPI\RelationalGridController.cs"/>
    </Samples>
    <Samples name ="ExcelLikeLayout">
      <dependantfiles displayname ="RelationalWebAPI" url="~\WebAPI\RelationalGridController.cs"/>
      <dependantfiles displayname ="OlapWebAPI" url="~\WebAPI\OlapGridController.cs"/>
    </Samples>
    <Samples name ="SaveAndLoad">
      <dependantfiles displayname ="RelationalWebAPI" url="~\WebAPI\RelationalGridController.cs"/>
      <dependantfiles displayname ="OlapWebAPI" url="~\WebAPI\OlapGridController.cs"/>
    </Samples>
    <Samples name ="SummaryCustomization">
      <dependantfiles displayname ="RelationalWebAPI" url="~\WebAPI\RelationalGridController.cs"/>
      <dependantfiles displayname ="OlapWebAPI" url="~\WebAPI\OlapGridController.cs"/>
    </Samples>
    <Samples name ="Paging">
      <dependantfiles displayname ="WebAPI" url="~\WebAPI\PagingController.cs"/>
    </Samples>
  </Controls>
  <Controls foldername ="UploadBox">
    <Samples name ="APIs" >
      <dependantfiles displayname ="saveFiles.ashx.cs" url="~\UploadBox\saveFiles.ashx.cs"/>
      <dependantfiles displayname ="removeFiles.ashx.cs" url="~\UploadBox\removeFiles.ashx.cs"/>
    </Samples>
    <Samples name ="DefaultFunctionalities" >
      <dependantfiles displayname ="saveFiles.ashx.cs" url="~\UploadBox\saveFiles.ashx.cs"/>
      <dependantfiles displayname ="removeFiles.ashx.cs" url="~\UploadBox\removeFiles.ashx.cs"/>
    </Samples>
    <Samples name ="Events" >
      <dependantfiles displayname ="saveFiles.ashx.cs" url="~\UploadBox\saveFiles.ashx.cs"/>
      <dependantfiles displayname ="removeFiles.ashx.cs" url="~\UploadBox\removeFiles.ashx.cs"/>
    </Samples>
    <Samples name ="FileInput" >
      <dependantfiles displayname ="saveFiles.ashx.cs" url="~\UploadBox\saveFiles.ashx.cs"/>
      <dependantfiles displayname ="removeFiles.ashx.cs" url="~\UploadBox\removeFiles.ashx.cs"/>
    </Samples>
    <Samples name ="DragAndDrop" >
      <dependantfiles displayname ="saveFiles.ashx.cs" url="~\UploadBox\saveFiles.ashx.cs"/>
      <dependantfiles displayname ="removeFiles.ashx.cs" url="~\UploadBox\removeFiles.ashx.cs"/>
    </Samples>
    <Samples name ="ClientSideEvents" >
      <dependantfiles displayname ="saveFiles.ashx.cs" url="~\UploadBox\saveFiles.ashx.cs"/>
      <dependantfiles displayname ="removeFiles.ashx.cs" url="~\UploadBox\removeFiles.ashx.cs"/>
    </Samples>
    <Samples name ="SynchronousUpload" >
      <dependantfiles displayname ="saveFiles.ashx.cs" url="~\UploadBox\saveFiles.ashx.cs"/>      
    </Samples>
  </Controls>
  <Controls foldername ="Grid">
    <Samples name ="AdaptiveGrid">
      <dependantfiles displayname ="Adaptive.aspx" url="~\Grid\Adaptive.aspx"/>
      <dependantfiles displayname ="Adaptive.aspx.cs" url="~\Grid\Adaptive.aspx.cs"/>
    </Samples>
    <Samples name ="XMLBinding">
      <dependantfiles displayname ="Catalog.xml" url="~\App_Data\Catalog.xml"/>
    </Samples>
  </Controls>
  <Controls foldername ="Gantt">
    <Samples name ="ObjectBinding">
      <dependantfiles displayname ="ObjectData.cs" url="~\App_Data\GanttObjectData.cs"/>
    </Samples>
    <Samples name ="XMLBinding">
      <dependantfiles displayname ="GanttData.xml" url="~\App_Data\GanttXML.xml"/>
    </Samples>
    <Samples name ="ScheduleModes">
      <dependantfiles displayname ="GanttData.js" url="~\Scripts\Gantt\GanttData.js"/>
    </Samples>
  </Controls>
  <Controls foldername ="TreeGrid">
    <Samples name ="ObjectBinding">
      <dependantfiles displayname ="ObjectData.cs" url="~\App_Data\TreeGridObjectData.cs"/>
    </Samples>
    <Samples name ="XMLBinding">
      <dependantfiles displayname ="TreeGridData.xml" url="~\App_Data\TreeGridXML.xml"/>
    </Samples>
    <Samples name ="Adaptive">
      <dependantfiles displayname ="AdaptiveTreeGrid.aspx" url="~\TreeGrid\AdaptiveTreegrid.aspx"/>
      <dependantfiles displayname ="AdaptiveTreeGrid.aspx.cs" url="~\TreeGrid\AdaptiveTreegrid.aspx.cs"/>
    </Samples>
  </Controls>
  <Controls foldername ="Diagram">
    <Samples name ="BPMNDiagram">
      <dependantfiles displayname ="BPMNDiagram.js" url="\Scripts\Diagram\BPMNDiagram.js"/> 
    </Samples>
     <Samples name ="Network">
      <dependantfiles displayname ="networkshapetemplates.js" url="\Scripts\Diagram\networkshapetemplates.js"/> 
    </Samples>
    <Samples name="ProductionAssembly">
      <dependantfiles displayname="productionassemblytemplates.js" url="\Scripts\Diagram\productionassemblytemplates.js"/>
      <dependantfiles displayname="ProductionAssembly.css" url="\Content\diagram\ProductionAssembly\ProductionAssembly.css"/>
    </Samples>
    <Samples name="Connectors">
      <dependantfiles displayname="Connectors.js" url="\Scripts\Diagram\Connectors.js"/>
    </Samples>
     <Samples name="Events">
      <dependantfiles displayname="eventlog.js" url="\Scripts\Diagram\eventlog.js"/>
    </Samples>
    <Samples name="HistoryManager">
      <dependantfiles displayname="HistoryManager.js" url="\Scripts\Diagram\HistoryManager.js"/>
    </Samples>
     <Samples name="LabelDiagram">
      <dependantfiles displayname="Label.js" url="\Scripts\Diagram\Label.js"/>
    </Samples>
    <Samples name="Model">
      <dependantfiles displayname="Model.js" url="\Scripts\Diagram\Model.js"/>
    </Samples>
    <Samples name="PageSettings">
      <dependantfiles displayname="PageSettings.js" url="\Scripts\Diagram\PageSettings.js"/>
    </Samples>
    <Samples name="PortDiagram">
      <dependantfiles displayname="Port.js" url="\Scripts\Diagram\Port.js"/>
    </Samples>
    <Samples name="DiagramShapes">
      <dependantfiles displayname="Shapes.js" url="\Scripts\Diagram\Shapes.js"/>
    </Samples>
    <Samples name="TooltipDiagram">
      <dependantfiles displayname="Tooltip.js" url="\Scripts\Diagram\Tooltip.js"/>
    </Samples>
    <Samples name="UserHandles">
      <dependantfiles displayname="UserHandles.js" url="\Scripts\Diagram\UserHandles.js"/>
    </Samples>
    <Samples name="DrawingTools">
      <dependantfiles displayname="drawingtools.css" url="\Content\diagram\drawingtools\drawingtools.css"/>
    </Samples>
    <Samples name="Editing">
      <dependantfiles displayname="editing.css" url="\Content\diagram\editing\editing.css"/>
    </Samples>
    <Samples name="SymbolPalette">
      <dependantfiles displayname="symbolpalette.css" url="\Content\diagram\symbolpalette\symbolpalette.css"/>
      <dependantfiles displayname="SymbolPalette.js" url="\Scripts\Diagram\SymbolPalette.js"/>
    </Samples>
    <Samples name="ZoomAndPan">
      <dependantfiles displayname="style.css" url="\Content\diagram\zoomandpan\style.css"/>
    </Samples>
    <Samples name ="TeamOrgChart">
      <dependantfiles displayname ="OrgChart.json" url="~\App_Data\OrgChart.json"/> 
    </Samples>
    <Samples name ="BusinessOrgChart">
      <dependantfiles displayname ="BusinessChart.json" url="~\App_Data\BusinessChart.json"/>
    </Samples>
    <Samples name ="LocalDataBinding">
      <dependantfiles displayname ="MarketChart.json" url="~\App_Data\MarketChart.json"/>
    </Samples>
    <Samples name ="MindMap">
      <dependantfiles displayname ="MindMap.json" url="~\App_Data\MindMap.json"/>
    </Samples>
    <Samples name ="ProjectManagementOrgChart">
      <dependantfiles displayname ="ProjectChart.json" url="~\App_Data\ProjectChart.json"/>
    </Samples>
    <Samples name ="UniversityOrgChart">
      <dependantfiles displayname ="UniversityChart.json" url="~\App_Data\UniversityChart.json"/>
    </Samples>
    <Samples name ="DrillDown">
      <dependantfiles displayname ="DrillDown.json" url="~\App_Data\DrillDown.json"/>
    </Samples>
    <Samples name ="HierarchicalLayout">
      <dependantfiles displayname ="HierarchicalLayout.json" url="~\App_Data\HierarchicalLayout.json"/>
      <dependantfiles displayname="HierarchicalLayout.js" url="\Scripts\Diagram\HierarchicalLayout.js"></dependantfiles>
    </Samples>
    <Samples name ="MultipleParent">
      <dependantfiles displayname ="MultipleParent.json" url="~\App_Data\MultipleParent.json"/>
      <dependantfiles displayname="multipleparent.js" url="\Scripts\Diagram\multipleparent.js"></dependantfiles>
    </Samples>
    <Samples name ="OrganizationChart">
      <dependantfiles displayname ="OrganizationChart.json" url="~\App_Data\OrganizationChart.json"/>
      <dependantfiles displayname="OrganizationalChart.js" url="\Scripts\Diagram\OrganizationalChart.js"></dependantfiles>
    </Samples>
    <Samples name ="RadialTree">
      <dependantfiles displayname ="RadialTree.json" url="~\App_Data\RadialData.json"/>
    </Samples>
     
  </Controls>
  <Controls foldername ="Dashboard">
    <Samples name="HealthTracker">
      <DependentFiles displayname="HealthTracker.aspx" url="Dashboard\HealthTracker.aspx"></DependentFiles>
      <DependentFiles displayname="HealthTracker.cs" url="Dashboard\HealthTracker.aspx.cs"></DependentFiles>
      <DependentFiles displayname="Healthtracker.js" url="Scripts\Dashboard\healthtracker.js"></DependentFiles>
    </Samples>
    <Samples name="ExpenseAnalysis">
      <DependentFiles displayname="ExpenseAnalysis.aspx" url="Dashboard\ExpenseAnalysis.aspx"></DependentFiles>
      <DependentFiles displayname="ExpenseAnalysis.cs" url="Dashboard\ExpenseAnalysis.aspx.cs"></DependentFiles>
    </Samples>
   <Samples name="ProjectTracker">
      <DependentFiles displayname="ProjectTracker.aspx" url="Dashboard\ProjectTracker.aspx"></DependentFiles>
      <DependentFiles displayname="ProjectTracker.cs" url="Dashboard\ProjectTracker.aspx.cs"></DependentFiles>
    </Samples>
	<Samples name="StockAnalysis">
      <DependentFiles displayname="StockAnalysis.aspx" url="Dashboard\StockAnalysis.aspx"></DependentFiles>
      <DependentFiles displayname="StockAnalysis.cs" url="Dashboard\StockAnalysis.aspx.cs"></DependentFiles>
    </Samples>
	<Samples name="WeatherAnalysis">
      <DependentFiles displayname="WeatherAnalysis.aspx" url="Dashboard\WeatherAnalysis.aspx"></DependentFiles>
      <DependentFiles displayname="WeatherAnalysis.cs" url="Dashboard\WeatherAnalysis.aspx.cs"></DependentFiles>
    </Samples>
	<Samples name="SalesAnalysis">
      <DependentFiles displayname="SalesAnalysis.aspx" url="Dashboard\SalesAnalysis.aspx"></DependentFiles>
      <DependentFiles displayname="SalesAnalysis.cs" url="Dashboard\SalesAnalysis.aspx.cs"></DependentFiles>
    </Samples>
    <Samples name="AirlineReservation">
      <DependentFiles displayname="AirlineReservation.aspx" url="Dashboard\AirlineReservation.aspx"></DependentFiles>
      <DependentFiles displayname="AirlineReservation.cs" url="Dashboard\AirlineReservation.aspx.cs"></DependentFiles>
      <DependentFiles displayname="Sample.js" url="Scripts\AirlineReservation\sample.js"></DependentFiles>
    </Samples>
	<Samples name="InvoiceTemplate">
      <DependentFiles displayname="InvoiceTemplate.aspx" url="Dashboard\InvoiceTemplate.aspx"></DependentFiles>
      <DependentFiles displayname="InvoiceTemplate.cs" url="Dashboard\InvoiceTemplate.aspx.cs"></DependentFiles>
    </Samples>
    <Samples name="SpreadsheetTemplate">
      <DependentFiles displayname="SpreadsheetTemplate.aspx" url="Dashboard\SpreadsheetTemplate.aspx"></DependentFiles>
      <DependentFiles displayname="SpreadsheetTemplate.cs" url="Dashboard\SpreadsheetTemplate.aspx.cs"></DependentFiles>
    </Samples>
  <Samples name="AuditShowcase">
      <DependentFiles displayname="AuditShowcase.aspx" url="Dashboard\AuditShowcase.aspx"></DependentFiles>
      <DependentFiles displayname="AuditShowcase.cs" url="Dashboard\AuditShowcase.aspx.cs"></DependentFiles>
    </Samples>
    <Samples name="AppointmentPlanner">
      <DependentFiles displayname="AppointmentPlanner.aspx" url="Dashboard\AppointmentPlanner.aspx"></DependentFiles>
      <DependentFiles displayname="AppointmentPlanner.cs" url="Dashboard\AppointmentPlanner.aspx.cs"></DependentFiles>      
    </Samples>   
  </Controls>
  <Controls foldername ="TreeView">
    <Samples name ="Databinding-Local" >
      <dependantfiles displayname ="TreeLocalDataSource.cs" url="~\App_Data\TreeView\TreeLocalDataSource.cs"/>
    </Samples>
    <Samples name ="DataBinding-Object" >
      <dependantfiles displayname ="TreeLocalDataSource.cs" url="~\App_Data\TreeView\TreeLocalDataSource.cs"/>
    </Samples>
    <Samples name ="DataBinding-Xml" >
      <dependantfiles displayname ="XMLData.xml" url="~\App_Data\XMLData.xml"/>
    </Samples>
    <Samples name ="FullRowSelection" >
      <dependantfiles displayname ="FullRowSelectDataSource.cs" url="~\App_Data\TreeView\FullRowSelectDataSource.cs"/>
    </Samples>
    <Samples name ="Icons" >
      <dependantfiles displayname ="TreeIconsDataSource.cs" url="~\App_Data\TreeView\TreeIconsDataSource.cs"/>
    </Samples>
    <Samples name ="LoadOnDemand" >
      <dependantfiles displayname ="TreeOnDemandDataSource.cs" url="~\App_Data\TreeView\TreeOnDemandDataSource.cs"/>
    </Samples>
    <Samples name ="MultiSelection" >
      <dependantfiles displayname ="MultiSelectDataSource.cs" url="~\App_Data\TreeView\MultiSelectDataSource.cs"/>
    </Samples>   
  </Controls>
   <Controls foldername ="Chart">
   <Samples name ="DefaultFunctionalities">
      <dependantfiles displayname ="linechartdata.cs" url="~\App_Data\LineChartData.cs"/> 
    </Samples>
    <Samples name ="StepLine">
      <dependantfiles displayname ="StepLineChartData.cs" url="~\App_Data\StepLineChartData.cs"/> 
    </Samples>
	 <Samples name ="Area">
      <dependantfiles displayname ="AreaChartData.cs" url="~\App_Data\Area.cs"/> 
    </Samples>
	<Samples name ="StepArea">
      <dependantfiles displayname ="StepAreaChartData.cs" url="~\App_Data\StepArea.cs"/> 
    </Samples>
	<Samples name ="SplineArea">
      <dependantfiles displayname ="SplineAreaChartData.cs" url="~\App_Data\SplineArea.cs"/> 
    </Samples>
	<Samples name ="StackingArea">
      <dependantfiles displayname ="StackingAreaChartData.cs" url="~\App_Data\StackingArea.cs"/> 
    </Samples>
	<Samples name ="StackingArea100">
      <dependantfiles displayname ="StackingArea100ChartData.cs" url="~\App_Data\StackingArea100.cs"/> 
    </Samples>
	<Samples name ="Column">
      <dependantfiles displayname ="ColumnChartData.cs" url="~\App_Data\Column.cs"/> 
    </Samples>
	<Samples name ="RangeColumn">
      <dependantfiles displayname ="RangeColumnChartData.cs" url="~\App_Data\RangeColumn.cs"/> 
    </Samples>
	<Samples name ="StackingColumn">
      <dependantfiles displayname ="StackingColumnChartData.cs" url="~\App_Data\StackingColumn.cs"/> 
    </Samples>
	<Samples name ="StackingColumn100">
      <dependantfiles displayname ="StackingColumn100ChartData.cs" url="~\App_Data\StackingColumn100.cs"/> 
    </Samples>
	<Samples name ="Bar">
      <dependantfiles displayname ="BarChartData.cs" url="~\App_Data\Bar.cs"/> 
    </Samples>
	<Samples name ="StackingBar">
      <dependantfiles displayname ="StackingBarChartData.cs" url="~\App_Data\StackingBar.cs"/> 
    </Samples>
	<Samples name ="StackingBar100">
      <dependantfiles displayname ="StackingBar100ChartData.cs" url="~\App_Data\StackingBar100.cs"/> 
    </Samples>
	<Samples name ="Spline">
    <dependantfiles displayname ="SplineChartData.cs" url="~\App_Data\Spline.cs"/> 
    </Samples>
   <Samples name ="Candle">
    <dependantfiles displayname ="CandleChartData.cs" url="~\App_Data\Candle.cs"/> 
    </Samples>
	<Samples name ="Hilo">
    <dependantfiles displayname ="HiloChartData.cs" url="~\App_Data\Hilo.cs"/> 
    </Samples>
	<Samples name ="HiloOpenClose">
    <dependantfiles displayname ="HiloOpenCloseChartData.cs" url="~\App_Data\HiloOpenClose.cs"/> 
    </Samples>
	<Samples name ="Polar">
    <dependantfiles displayname ="PolarChartData.cs" url="~\App_Data\Polar.cs"/> 
    </Samples>
	<Samples name ="Radar">
    <dependantfiles displayname ="RadarChartData.cs" url="~\App_Data\Radar.cs"/> 
    </Samples>
	<Samples name ="WindRose">
    <dependantfiles displayname ="WindRoseChartData.cs" url="~\App_Data\WindRose.cs"/> 
    </Samples>
	<Samples name ="BoxPlot">
    <dependantfiles displayname ="BoxPlotChartData.cs" url="~\App_Data\BoxPlot.cs"/> 
    </Samples>
	<Samples name ="Combination">
    <dependantfiles displayname ="CombinationChartData.cs" url="~\App_Data\Combination.cs"/> 
    </Samples>
	<Samples name ="ErrorBar">
    <dependantfiles displayname ="ErrorBarChartData.cs" url="~\App_Data\ErrorBar.cs"/> 
    </Samples>
   <Samples name ="MultipleAxes">
    <dependantfiles displayname ="MultiDatta.cs" url="~\App_Data\MultipleAxes.cs"/> 
    </Samples>
	<Samples name ="Title">
    <dependantfiles displayname ="TrimAxisData.cs" url="~\App_Data\Title.cs"/> 
    </Samples>
	<Samples name ="StripLineSample">
    <dependantfiles displayname ="StripData.cs" url="~\App_Data\StripLine.cs"/> 
    </Samples>
	<Samples name ="DateTimeAxis">
    <dependantfiles displayname ="DatetimeData.cs" url="~\App_Data\DateTimeAxis.cs"/> 
    </Samples>
	<Samples name ="Isindexed">
    <dependantfiles displayname ="IsindexedChartData.cs" url="~\App_Data\Isindexed.cs"/> 
    </Samples>
	<Samples name ="LogAxis">
    <dependantfiles displayname ="LogData.cs" url="~\App_Data\LogAxis.cs"/> 
    </Samples>
	<Samples name ="SmartAxisLabel">
    <dependantfiles displayname ="SmartAxisData.cs" url="~\App_Data\SmartAxisLabel.cs"/> 
    </Samples>
	<Samples name ="InversedAxis">
    <dependantfiles displayname ="InversedData.cs" url="~\App_Data\InversedAxis.cs"/> 
    </Samples>
	<Samples name ="AlternateGridBand">
    <dependantfiles displayname ="AlternateGridBandData.cs" url="~\App_Data\AlternateGridBand.cs"/> 
    </Samples>
	<Samples name ="DateTimecategoryAxis">
    <dependantfiles displayname ="DateTimeDate.cs" url="~\App_Data\DateTimecategoryAxis.cs"/> 
    </Samples>
    <Samples name ="Symbols">
    <dependantfiles displayname ="SymbolDate.cs" url="~\App_Data\Symbol.cs"/> 
    </Samples>
	<Samples name ="ToolTipTemplate">
    <dependantfiles displayname ="TooltipData.cs" url="~\App_Data\ToolTipTemplate.cs"/> 
    </Samples>
	<Samples name ="SmartLabels">
    <dependantfiles displayname ="SmartLabelsData.cs" url="~\App_Data\SmartLabels.cs"/> 
    </Samples>
	<Samples name ="Annotations">
    <dependantfiles displayname ="AnnotationChartData.cs" url="~\App_Data\Annotation.cs"/> 
    </Samples>
	<Samples name ="LegendPosition1">
    <dependantfiles displayname ="LocalData.cs" url="~\App_Data\LegendPosition1.cs"/> 
    </Samples>
	<Samples name ="SubTitle">
    <dependantfiles displayname ="SubTitleData.cs" url="~\App_Data\SubTitle.cs"/> 
    </Samples>
	<Samples name ="Selection">
    <dependantfiles displayname ="SelectionChartData.cs" url="~\App_Data\Selection.cs"/> 
    </Samples>
	<Samples name ="TrackBall">
    <dependantfiles displayname ="TrackBallData.cs" url="~\App_Data\TrackBall.cs"/> 
    </Samples>
	<Samples name ="Events">
    <dependantfiles displayname ="EventData.cs" url="~\App_Data\Event.cs"/> 
    </Samples>
	<Samples name ="Zooming">
    <dependantfiles displayname ="Zooming.cs" url="~\App_Data\Zooming.cs"/> 
    </Samples>
	<Samples name ="DragDrop">
    <dependantfiles displayname ="DatetimeData1.cs" url="~\App_Data\DragDrop.cs"/> 
    </Samples>
</Controls>
  <Controls foldername ="AutoComplete">
    <Samples name ="DefaultFunctionalities">
      <dependantfiles displayname ="CarsList.cs" url="~\App_Data\CarsList.cs"/>
    </Samples>
	<Samples name ="MultipleValues">
      <dependantfiles displayname ="Lanuages.cs" url="~\App_Data\Lanuages.cs"/>
    </Samples>
	<Samples name ="Grouping">
      <dependantfiles displayname ="Countries.cs" url="~\App_Data\Countries.cs"/>
    </Samples>
	<Samples name ="Template">
      <dependantfiles displayname ="Flags.cs" url="~\App_Data\Flags.cs"/>
    </Samples>
	<Samples name ="Databinding-Local">
      <dependantfiles displayname ="States.cs" url="~\App_Data\States.cs"/>
    </Samples>
	<Samples name ="DataBinding-ObjectData">
      <dependantfiles displayname ="TabData.cs" url="~\App_Data\TabData.cs"/>
    </Samples>
	<Samples name ="DataBinding-XMLData">
      <dependantfiles displayname ="XMLData.xml" url="~\App_Data\XMLData.xml"/>
    </Samples>
	<Samples name ="AutoFill">
      <dependantfiles displayname ="Flowers.cs" url="~\App_Data\Flowers.cs"/>
    </Samples>
	<Samples name ="APIs">
      <dependantfiles displayname ="Countries.cs" url="~\App_Data\Countries.cs"/>
    </Samples>
	<Samples name ="ClientSideEvents">
      <dependantfiles displayname ="Colors.cs" url="~\App_Data\Colors.cs"/>
    </Samples>
	<Samples name ="Events">
      <dependantfiles displayname ="Colors.cs" url="~\App_Data\Colors.cs"/>
    </Samples>
	<Samples name ="RTL">
      <dependantfiles displayname ="CarsList.cs" url="~\App_Data\CarsList.cs"/>
    </Samples>
	<Samples name ="KeyboardInteractions">
      <dependantfiles displayname ="Lanuages.cs" url="~\App_Data\Lanuages.cs"/>
    </Samples>
  </Controls>
  <Controls foldername ="ListBox">
    <Samples name ="DataBinding-ObjectData">
      <dependantfiles displayname ="TabData.cs" url="~\App_Data\TabData.cs"/>
    </Samples>
	<Samples name ="DataBinding-XMLData">
      <dependantfiles displayname ="ListBoxXml.xml" url="~\App_Data\ListBoxXml.xml"/>
    </Samples>
	<Samples name ="DataBinding-locatdata">
      <dependantfiles displayname ="TabData.cs" url="~\App_Data\TabData.cs"/>
    </Samples>
  </Controls>
  <Controls foldername ="ListView">
    <Samples name ="DataBinding-ObjectData">
      <dependantfiles displayname ="TabData.cs" url="~\App_Data\TabData.cs"/>
    </Samples>
	<Samples name ="DataBinding-XMLData">
      <dependantfiles displayname ="XMLData.xml" url="~\App_Data\XMLData.xml"/>
    </Samples>
	<Samples name ="Template">
      <dependantfiles displayname ="ListViewData.cs" url="~\App_Data\ListViewData.cs"/>
    </Samples>
  </Controls>
  <Controls foldername ="Rotator">
    <Samples name ="Databinding-Local">
      <dependantfiles displayname ="RotatorData.cs" url="~\App_Data\RotatorData.cs"/>
    </Samples>
  </Controls>
  <Controls foldername ="Spreadsheet">
    <Samples name="Adaptive">
    <dependantfiles displayname="itemdata.cs" url="Model\ItemData.cs"/>    
  </Samples>
  <Samples name="Border">
    <dependantfiles displayname="borderdata.cs" url="Model\BorderData.cs"/>    
  </Samples>
  <Samples name="CellFormatting">
    <dependantfiles displayname="cellformatdata.cs" url="Model\CellFormatData.cs"/>    
  </Samples>
  <Samples name="CellType">
    <dependantfiles displayname="celltypedata.cs" url="Model\CellTypeData.cs"/>    
  </Samples>
  <Samples name="Chart">
    <dependantfiles displayname="markdata.cs" url="Model\MarkDetail.cs"/>    
  </Samples>
  <Samples name="ConditionalFormatting">
    <dependantfiles displayname="conditionalformatdata.cs" url="Model\ConditionalFormatData.cs"/>    
  </Samples>
  <Samples name="ContextMenu">
    <dependantfiles displayname="markdata.cs" url="Model\MarkDetail.cs"/>
  </Samples>
  <Samples name="DataValidation">
    <dependantfiles displayname="datavalidationdata.cs" url="Model\DataValidationData.cs"/>
  </Samples>
  <Samples name="DefaultFunctionalities">
    <dependantfiles displayname="itemdata.cs" url="Model\ItemData.cs"/>
  </Samples>
  <Samples name="Formula">
    <dependantfiles displayname="formuladata.cs" url="Model\FormulaData.cs"/>
  </Samples>
  <Samples name="FreezePane">
    <dependantfiles displayname="persondata.cs" url="Model\PersonDetail.cs"/>    
  </Samples>
  <Samples name="Hyperlink">
    <dependantfiles displayname="hyperlinkdata.cs" url="Model\HyperlinkData.cs"/>    
  </Samples>
  <Samples name="MergeCell">
    <dependantfiles displayname="mergedata.cs" url="Model\MergeData.cs"/> 
  </Samples>
  <Samples name="MLTemplate">
    <dependantfiles displayname="moviedata.cs" url="Model\MovieData.cs"/>    
  </Samples>
   <Samples name="NumberFormatting">
    <dependantfiles displayname="numberformatdata.cs" url="Model\NumberFormatData.cs"/>    
  </Samples>
  <Samples name="Pivot">
    <dependantfiles displayname="pivotdata.cs" url="Model\PivotData.cs"/>    
  </Samples>
  <Samples name="Sparkline">
    <dependantfiles displayname="sparklinedata.cs" url="Model\SparklineDetail.cs"/>
  </Samples>
  <Samples name="Table">
    <dependantfiles displayname="tabledata.cs" url="Model\TableData.cs"/>
  </Samples>
  <Samples name="Templates">
    <dependantfiles displayname="fifadata.cs" url="Model\FIFAData.cs"/>    
  </Samples>
  </Controls>
</SourceTabSettings>
